pyatagone/__init__.py
pyatagone/atagoneapi.py
pyatagone/atagoneentity.py
pyatagone/atagonejson.py
pyatagone/client.py
pyatagone/configuration.py
pyatagone/const.py
pyatagone/exceptions.py
pyatagone-1.0.12.dist-info/METADATA
pyatagone-1.0.12.dist-info/WHEEL
pyatagone-1.0.12.dist-info/licenses/AUTHORS.rst
pyatagone-1.0.12.dist-info/licenses/LICENSE
pyatagone-1.0.12.dist-info/licenses/LICENSE.txt
pyatagone-1.0.12.dist-info/RECORD
